{"openapi":"3.0.0","info":{"title":"Demo API","version":"1.0.0"},"servers":[{"url":"http://localhost:3001/api/v1"}],"paths":{"/home-sections":{"get":{"description":"","responses":{"200":{"description":"","content":{"application/json":{}},"headers":{"Access-Control-Allow-Origin":{"schema":{"type":"string"},"example":"http://localhost:3000"},"Access-Control-Allow-Credentials":{"schema":{"type":"string"},"example":"true"}}}}}},"/products":{"get":{"description":"","responses":{"200":{"description":"","content":{"application/json":{}},"headers":{"Access-Control-Allow-Origin":{"schema":{"type":"string"},"example":"http://localhost:3000"},"Access-Control-Allow-Credentials":{"schema":{"type":"string"},"example":"true"}}}}}},"/products/men":{"get":{"description":"","responses":{"200":{"description":"","content":{"application/json":{}},"headers":{"Access-Control-Allow-Origin":{"schema":{"type":"string"},"example":"http://localhost:3000"},"Access-Control-Allow-Credentials":{"schema":{"type":"string"},"example":"true"}}}}}},"/products/women":{"get":{"description":"","responses":{"200":{"description":"","content":{"application/json":{}},"headers":{"Access-Control-Allow-Origin":{"schema":{"type":"string"},"example":"http://localhost:3000"},"Access-Control-Allow-Credentials":{"schema":{"type":"string"},"example":"true"}}}}}},"/products/kids":{"get":{"description":"","responses":{"200":{"description":"","content":{"application/json":{}},"headers":{"Access-Control-Allow-Origin":{"schema":{"type":"string"},"example":"http://localhost:3000"},"Access-Control-Allow-Credentials":{"schema":{"type":"string"},"example":"true"}}}}}},"/product":{"get":{"description":"","responses":{"200":{"description":"","content":{"application/json":{}},"headers":{"Access-Control-Allow-Origin":{"schema":{"type":"string"},"example":"http://localhost:3000"},"Access-Control-Allow-Credentials":{"schema":{"type":"string"},"example":"true"}}}}}},"/login":{"post":{"description":"","responses":{"200":{"description":"","content":{"application/json":{}},"headers":{"Access-Control-Allow-Origin":{"schema":{"type":"string"},"example":"http://localhost:3000"},"Access-Control-Allow-Credentials":{"schema":{"type":"string"},"example":"true"}}}}}}}}